simpleautocad/Utility.py
simpleautocad/Utility.pyi
simpleautocad/__init__.py
simpleautocad/__init__.pyi
simpleautocad/Autocad/AcadEntity.py
simpleautocad/Autocad/AcadEntity.pyi
simpleautocad/Autocad/AcadObject.py
simpleautocad/Autocad/AcadObject.pyi
simpleautocad/Autocad/Base.py
simpleautocad/Autocad/Base.pyi
simpleautocad/Autocad/Proxy.py
simpleautocad/Autocad/Proxy.pyi
simpleautocad/Autocad/__init__.py
simpleautocad/Autocad/__init__.pyi
simpleautocad/Autocad/Entities/Acad3DFace.py
simpleautocad/Autocad/Entities/Acad3DFace.pyi
simpleautocad/Autocad/Entities/Acad3DPolyline.py
simpleautocad/Autocad/Entities/Acad3DPolyline.pyi
simpleautocad/Autocad/Entities/Acad3DSolid.py
simpleautocad/Autocad/Entities/Acad3DSolid.pyi
simpleautocad/Autocad/Entities/AcadArc.py
simpleautocad/Autocad/Entities/AcadArc.pyi
simpleautocad/Autocad/Entities/AcadAttribute.py
simpleautocad/Autocad/Entities/AcadAttribute.pyi
simpleautocad/Autocad/Entities/AcadAttributeReference.py
simpleautocad/Autocad/Entities/AcadAttributeReference.pyi
simpleautocad/Autocad/Entities/AcadBlockReference.py
simpleautocad/Autocad/Entities/AcadBlockReference.pyi
simpleautocad/Autocad/Entities/AcadCircle.py
simpleautocad/Autocad/Entities/AcadCircle.pyi
simpleautocad/Autocad/Entities/AcadComparedReference.py
simpleautocad/Autocad/Entities/AcadComparedReference.pyi
simpleautocad/Autocad/Entities/AcadDgnUnderlay.py
simpleautocad/Autocad/Entities/AcadDgnUnderlay.pyi
simpleautocad/Autocad/Entities/AcadDim3PointAngular.py
simpleautocad/Autocad/Entities/AcadDim3PointAngular.pyi
simpleautocad/Autocad/Entities/AcadDimAligned.py
simpleautocad/Autocad/Entities/AcadDimAligned.pyi
simpleautocad/Autocad/Entities/AcadDimAngular.py
simpleautocad/Autocad/Entities/AcadDimAngular.pyi
simpleautocad/Autocad/Entities/AcadDimArcLength.py
simpleautocad/Autocad/Entities/AcadDimArcLength.pyi
simpleautocad/Autocad/Entities/AcadDimDiametric.py
simpleautocad/Autocad/Entities/AcadDimDiametric.pyi
simpleautocad/Autocad/Entities/AcadDimOrdinate.py
simpleautocad-0.0.1b5.dist-info/METADATA
simpleautocad-0.0.1b5.dist-info/WHEEL
simpleautocad-0.0.1b5.dist-info/top_level.txt
simpleautocad-0.0.1b5.dist-info/RECORD
