Metadata-Version: 2.4
Name: simpleautocad
Version: 0.0.1b5
Summary: Модуль для работы с AutoCAD через COM интерфейс
Author-email: Andrey Litvinov <busybeaver.bb@gmail.com>
Classifier: Programming Language :: Python :: 3
Classifier: License :: OSI Approved :: MIT License
Classifier: Operating System :: Microsoft :: Windows
Requires-Python: >=3.13
Requires-Dist: pywin32
Requires-Dist: numpy
